__init__.py
pasteme_cli/__init__.py
pasteme_cli/__main__.py
pasteme_cli/cli.py
pasteme_cli/constants.py
pasteme_cli/shapes.py
pasteme_cli/sdk/__init__.py
pasteme_cli/sdk/pasteme.py
pasteme_cli/sdk/types.py
pasteme_cli-1.0.6.dist-info/AUTHORS.rst
pasteme_cli-1.0.6.dist-info/LICENSE
pasteme_cli-1.0.6.dist-info/METADATA
pasteme_cli-1.0.6.dist-info/WHEEL
pasteme_cli-1.0.6.dist-info/entry_points.txt
pasteme_cli-1.0.6.dist-info/top_level.txt
pasteme_cli-1.0.6.dist-info/RECORD
