Metadata-Version: 2.1
Name: pasteme-cli
Version: 1.0.6
Summary: A CLI pastebin tool.
Home-page: https://github.com/collove/pasteme-cli
Author: Sadra Yahyapour
Author-email: lnxpylnxpy@gmail.com
License: MIT
Project-URL: Documentation, https://pasteme-cli.readthedocs.io/
Project-URL: Changelog, https://pasteme-cli.readthedocs.io/en/latest/changelog.html
Project-URL: Issue Tracker, https://github.com/collove/pasteme-cli/issues
Keywords: pastebin,cli,tool,linux
Classifier: Development Status :: 5 - Production/Stable
Classifier: Intended Audience :: Developers
Classifier: License :: OSI Approved :: MIT License
Classifier: Operating System :: Unix
Classifier: Operating System :: POSIX
Classifier: Operating System :: Microsoft :: Windows
Classifier: Programming Language :: Python
Classifier: Programming Language :: Python :: 3
Classifier: Programming Language :: Python :: 3 :: Only
Classifier: Programming Language :: Python :: 3.7
Classifier: Programming Language :: Python :: 3.8
Classifier: Programming Language :: Python :: 3.9
Classifier: Programming Language :: Python :: 3.10
Classifier: Programming Language :: Python :: Implementation :: CPython
Classifier: Programming Language :: Python :: Implementation :: PyPy
Classifier: Topic :: Utilities
Requires-Python: >=3.7
License-File: LICENSE
License-File: AUTHORS.rst
Requires-Dist: requests (==2.28.1)
Requires-Dist: Pygments (==2.12.0)
